pz_rail_cmnn-1.1.1.dist-info/licenses/LICENSE
rail/cmnn/__init__.py
rail/cmnn/_version.py
rail/estimation/algos/cmnn.py
pz_rail_cmnn-1.1.1.dist-info/METADATA
pz_rail_cmnn-1.1.1.dist-info/WHEEL
pz_rail_cmnn-1.1.1.dist-info/top_level.txt
pz_rail_cmnn-1.1.1.dist-info/RECORD
