Metadata-Version: 2.4
Name: pz-rail-cmnn
Version: 1.1.1
Author-email: "LSST Dark Energy Science Collaboration (DESC)" <later@later.com>
License: MIT License
Classifier: Development Status :: 4 - Beta
Classifier: License :: OSI Approved :: MIT License
Classifier: Intended Audience :: Developers
Classifier: Intended Audience :: Science/Research
Classifier: Operating System :: OS Independent
Classifier: Programming Language :: Python
Requires-Python: >=3.10
License-File: LICENSE
Requires-Dist: ceci
Requires-Dist: numpy
Requires-Dist: scipy>=1.9
Requires-Dist: pz-rail-base>=1.0.3
Provides-Extra: dev
Requires-Dist: qp-prob[full]; extra == "dev"
Requires-Dist: coverage; extra == "dev"
Requires-Dist: pylint; extra == "dev"
Requires-Dist: pytest; extra == "dev"
Requires-Dist: pytest-cov; extra == "dev"
Requires-Dist: yamllint; extra == "dev"
Dynamic: license-file
